{
  "nodes": [
    {"id": "server_api_users_usersRouter", "label": "usersRouter (api/users)", "file_type": "code", "source_file": "server/api/users.ts", "source_location": "L7", "source_url": null, "captured_at": null, "author": null, "contributor": null},
    {"id": "server_api_users_requireAuthMiddleware", "label": "requireAuth applied to all /api/users routes", "file_type": "code", "source_file": "server/api/users.ts", "source_location": "L8", "source_url": null, "captured_at": null, "author": null, "contributor": null},
    {"id": "server_api_users_roleBasedTableSelect", "label": "tableForRole — routes to coaches/parents/players by JWT role", "file_type": "code", "source_file": "server/api/users.ts", "source_location": "L16-L20", "source_url": null, "captured_at": null, "author": null, "contributor": null},
    {"id": "server_api_users_passwordHashStrip", "label": "passwordHash stripped from all profile responses", "file_type": "code", "source_file": "server/api/users.ts", "source_location": "L35,L64", "source_url": null, "captured_at": null, "author": null, "contributor": null},
    {"id": "server_api_users_athleteOnlyProfileWrite", "label": "PUT /profile restricted to role=athlete only", "file_type": "code", "source_file": "server/api/users.ts", "source_location": "L47-L49", "source_url": null, "captured_at": null, "author": null, "contributor": null},
    {"id": "server_auth_TokenPayload", "label": "TokenPayload interface (userId, email, role, name)", "file_type": "code", "source_file": "server/auth.ts", "source_location": "L11-L16", "source_url": null, "captured_at": null, "author": null, "contributor": null},
    {"id": "server_auth_UserRole", "label": "UserRole type: athlete | coach | parent | admin", "file_type": "code", "source_file": "server/auth.ts", "source_location": "L9", "source_url": null, "captured_at": null, "author": null, "contributor": null},
    {"id": "server_auth_jwtBearerMiddleware", "label": "requireAuth — Bearer JWT extraction and verification middleware", "file_type": "code", "source_file": "server/auth.ts", "source_location": "L34-L48", "source_url": null, "captured_at": null, "author": null, "contributor": null},
    {"id": "server_auth_requireAdmin", "label": "requireAdmin — chains requireAuth then checks role=admin", "file_type": "code", "source_file": "server/auth.ts", "source_location": "L50-L59", "source_url": null, "captured_at": null, "author": null, "contributor": null},
    {"id": "server_auth_requireCoach", "label": "requireCoach — chains requireAuth then checks role=coach", "file_type": "code", "source_file": "server/auth.ts", "source_location": "L65-L74", "source_url": null, "captured_at": null, "author": null, "contributor": null},
    {"id": "server_auth_verifyGoogleToken", "label": "verifyGoogleToken — validates Google OAuth2 ID token via OAuth2Client", "file_type": "code", "source_file": "server/auth.ts", "source_location": "L76-L92", "source_url": null, "captured_at": null, "author": null, "contributor": null},
    {"id": "server_auth_signToken", "label": "signToken / verifyToken — JWT sign + verify with JWT_SECRET", "file_type": "code", "source_file": "server/auth.ts", "source_location": "L26-L32", "source_url": null, "captured_at": null, "author": null, "contributor": null},
    {"id": "server_auth_bcryptHashCompare", "label": "hashPassword / comparePassword — bcrypt 12 rounds", "file_type": "code", "source_file": "server/auth.ts", "source_location": "L18-L23", "source_url": null, "captured_at": null, "author": null, "contributor": null},
    {"id": "server_authRoutes_loginRateLimiter", "label": "loginLimiter — 20 req/15min rate limiter on login + google routes", "file_type": "code", "source_file": "server/authRoutes.ts", "source_location": "L10-L16", "source_url": null, "captured_at": null, "author": null, "contributor": null},
    {"id": "server_authRoutes_registerFlow", "label": "POST /api/auth/register — role-branched insert into coaches/parents/players then JWT", "file_type": "code", "source_file": "server/authRoutes.ts", "source_location": "L48-L95", "source_url": null, "captured_at": null, "author": null, "contributor": null},
    {"id": "server_authRoutes_loginFlow", "label": "POST /api/auth/login — bcrypt compare then JWT issue", "file_type": "code", "source_file": "server/authRoutes.ts", "source_location": "L99-L118", "source_url": null, "captured_at": null, "author": null, "contributor": null},
    {"id": "server_authRoutes_googleOAuthFlow", "label": "POST /api/auth/google — Google token verify then upsert user then JWT", "file_type": "code", "source_file": "server/authRoutes.ts", "source_location": "L122-L169", "source_url": null, "captured_at": null, "author": null, "contributor": null},
    {"id": "server_authRoutes_statelessLogout", "label": "POST /api/auth/logout — stateless (no server-side session), client drops JWT", "file_type": "code", "source_file": "server/authRoutes.ts", "source_location": "L179-L182", "source_url": null, "captured_at": null, "author": null, "contributor": null},
    {"id": "server_cache_layer_RedisCacheClient", "label": "RedisCacheClient — Redis get/set/delete with JSON serialization and metrics", "file_type": "code", "source_file": "server/cache-layer.ts", "source_location": "L65-L211", "source_url": null, "captured_at": null, "author": null, "contributor": null},
    {"id": "server_cache_layer_HybridCacheManager", "label": "HybridCacheManager — Redis-first cache-aside + write-through over CosmosDB", "file_type": "code", "source_file": "server/cache-layer.ts", "source_location": "L215-L602", "source_url": null, "captured_at": null, "author": null, "contributor": null},
    {"id": "server_cache_layer_cacheAside", "label": "CacheAsideManager — generic get/set/invalidate wrapper", "file_type": "code", "source_file": "server/cache-layer.ts", "source_location": "L606-L669", "source_url": null, "captured_at": null, "author": null, "contributor": null},
    {"id": "server_cache_layer_invalidateUserRelatedCaches", "label": "invalidateUserRelatedCaches — deletes user, user_posts, user_search, user_analytics keys on write", "file_type": "code", "source_file": "server/cache-layer.ts", "source_location": "L296-L305", "source_url": null, "captured_at": null, "author": null, "contributor": null},
    {"id": "server_cache_layer_ttlConfig", "label": "Cache TTL config: user=5m, post=10m, search=30m, analytics=1h, session=1h", "file_type": "code", "source_file": "server/cache-layer.ts", "source_location": "L39-L49", "source_url": null, "captured_at": null, "author": null, "contributor": null},
    {"id": "server_cloud_config_cloudConfig", "label": "cloudConfig — multi-cloud provider/region config (AWS/GCP/Azure)", "file_type": "code", "source_file": "server/cloud-config.ts", "source_location": null, "source_url": null, "captured_at": null, "author": null, "contributor": null},
    {"id": "server_cloud_routes_cloudRouter", "label": "cloudRouter — /health, /status, /config endpoints", "file_type": "code", "source_file": "server/cloud-routes.ts", "source_location": null, "source_url": null, "captured_at": null, "author": null, "contributor": null},
    {"id": "server_cloud_storage_uploadVideo", "label": "uploadVideo — S3/Cloudfront video upload with timestamp-prefixed key", "file_type": "code", "source_file": "server/cloud-storage.ts", "source_location": "L23-L38", "source_url": null, "captured_at": null, "author": null, "contributor": null},
    {"id": "server_cloud_storage_uploadImage", "label": "uploadImage — S3/Cloudfront image upload", "file_type": "code", "source_file": "server/cloud-storage.ts", "source_location": "L40-L55", "source_url": null, "captured_at": null, "author": null, "contributor": null},
    {"id": "server_cloud_storage_signedUrls", "label": "getSignedUploadUrl / getSignedDownloadUrl — presigned S3 URLs (default 1h expiry)", "file_type": "code", "source_file": "server/cloud-storage.ts", "source_location": "L57-L74", "source_url": null, "captured_at": null, "author": null, "contributor": null},
    {"id": "server_coachRoutes_requireCoachGate", "label": "coachRouter applies requireCoach middleware to all routes", "file_type": "code", "source_file": "server/coachRoutes.ts", "source_location": "L16", "source_url": null, "captured_at": null, "author": null, "contributor": null},
    {"id": "server_coachRoutes_scoutingBoard", "label": "Scouting board CRUD — coachProspects table with tier (top-target/watching/offered)", "file_type": "code", "source_file": "server/coachRoutes.ts", "source_location": "L195-L331", "source_url": null, "captured_at": null, "author": null, "contributor": null},
    {"id": "server_coachRoutes_coachToAthleteMessage", "label": "POST /coach/message/:playerId — coach sends message to athlete (no parent gate at route level)", "file_type": "code", "source_file": "server/coachRoutes.ts", "source_location": "L338-L358", "source_url": null, "captured_at": null, "author": null, "contributor": null},
    {"id": "server_coachRoutes_playerSearchMockData", "label": "Coach player search currently returns mock data (TODO: replace with real DB query)", "file_type": "code", "source_file": "server/coachRoutes.ts", "source_location": "L63-L100", "source_url": null, "captured_at": null, "author": null, "contributor": null},
    {"id": "server_compliance_monitoring_ComplianceMonitor", "label": "ComplianceMonitor — scheduled COPPA/FERPA/GDPR checks every 4h + realtime every 5min", "file_type": "code", "source_file": "server/compliance-monitoring.ts", "source_location": "L23-L665", "source_url": null, "captured_at": null, "author": null, "contributor": null},
    {"id": "server_compliance_monitoring_COPPACheck", "label": "checkCOPPACompliance — checks parental consent coverage, data minimization, deletion requests", "file_type": "code", "source_file": "server/compliance-monitoring.ts", "source_location": "L140-L181", "source_url": null, "captured_at": null, "author": null, "contributor": null},
    {"id": "server_compliance_monitoring_FERPACheck", "label": "checkFERPACompliance — checks parental access, coach access restrictions, data sharing", "file_type": "code", "source_file": "server/compliance-monitoring.ts", "source_location": "L183-L223", "source_url": null, "captured_at": null, "author": null, "contributor": null},
    {"id": "server_compliance_monitoring_GDPRCheck", "label": "checkGDPRCompliance — checks consent, portability, erasure, 72h breach notification", "file_type": "code", "source_file": "server/compliance-monitoring.ts", "source_location": "L225-L279", "source_url": null, "captured_at": null, "author": null, "contributor": null},
    {"id": "server_compliance_monitoring_violationPublish", "label": "reportViolation — stores to Cosmos audit-logs + publishes ComplianceViolationDetected to Service Bus", "file_type": "code", "source_file": "server/compliance-monitoring.ts", "source_location": "L460-L499", "source_url": null, "captured_at": null, "author": null, "contributor": null},
    {"id": "server_compliance_monitoring_ComplianceAlerting", "label": "ComplianceAlerting — wraps ComplianceMonitor to send violation/breach alerts", "file_type": "code", "source_file": "server/compliance-monitoring.ts", "source_location": "L669-L723", "source_url": null, "captured_at": null, "author": null, "contributor": null},
    {"id": "server_compliance_orchestrator_ComplianceOrchestrator", "label": "ComplianceOrchestrator — wires ComplianceService, DataExportPipeline, DataDeletionPipeline, ComplianceMonitor", "file_type": "code", "source_file": "server/compliance-orchestrator.ts", "source_location": "L22-L352", "source_url": null, "captured_at": null, "author": null, "contributor": null},
    {"id": "server_compliance_orchestrator_serviceBusEventHandlers", "label": "Service Bus topic subscriptions: DataExportRequested, DataDeletionRequested, ComplianceViolationDetected", "file_type": "code", "source_file": "server/compliance-orchestrator.ts", "source_location": "L122-L201", "source_url": null, "captured_at": null, "author": null, "contributor": null},
    {"id": "server_compliance_orchestrator_compliancePort4001", "label": "ComplianceOrchestrator HTTP server listens on port 4001 (separate from core API :4000)", "file_type": "code", "source_file": "server/compliance-orchestrator.ts", "source_location": "L219", "source_url": null, "captured_at": null, "author": null, "contributor": null},
    {"id": "server_compliance_orchestrator_ComplianceDashboard", "label": "ComplianceDashboard — aggregates orchestrator status, compliance checks, and data processing stats", "file_type": "code", "source_file": "server/compliance-orchestrator.ts", "source_location": "L356-L415", "source_url": null, "captured_at": null, "author": null, "contributor": null},
    {"id": "server_compliance_orchestrator_ComplianceUtils", "label": "ComplianceUtils — COPPA age validation, retention period lookup, parental consent check", "file_type": "code", "source_file": "server/compliance-orchestrator.ts", "source_location": "L419-L511", "source_url": null, "captured_at": null, "author": null, "contributor": null},
    {"id": "server_compliance_service_ComplianceService", "label": "ComplianceService — RBAC, consent management, data export/deletion, audit logging Express app", "file_type": "code", "source_file": "server/compliance-service.ts", "source_location": "L30-L627", "source_url": null, "captured_at": null, "author": null, "contributor": null},
    {"id": "server_compliance_service_rbacMiddleware", "label": "rbacMiddleware — header-based userId/userType RBAC check with audit logging on every access", "file_type": "code", "source_file": "server/compliance-service.ts", "source_location": "L113-L193", "source_url": null, "captured_at": null, "author": null, "contributor": null},
    {"id": "server_compliance_service_AuditChain", "label": "AuditChain — SHA-256 hash chain for immutable audit log integrity verification", "file_type": "code", "source_file": "server/compliance-service.ts", "source_location": "L631-L658", "source_url": null, "captured_at": null, "author": null, "contributor": null},
    {"id": "server_compliance_service_dataExportRequest", "label": "requestDataExport — creates export request in Cosmos + publishes DataExportRequested event", "file_type": "code", "source_file": "server/compliance-service.ts", "source_location": "L274-L353", "source_url": null, "captured_at": null, "author": null, "contributor": null},
    {"id": "server_compliance_service_dataDeletionRequest", "label": "requestDataDeletion — framework-validated deletion request (COPPA/FERPA/GDPR rules differ)", "file_type": "code", "source_file": "server/compliance-service.ts", "source_location": "L355-L445", "source_url": null, "captured_at": null, "author": null, "contributor": null},
    {"id": "server_compliance_service_correlationIdMiddleware", "label": "correlationId middleware — extracts x-correlation-id/x-request-id or generates UUID per request", "file_type": "code", "source_file": "server/compliance-service.ts", "source_location": "L53-L60", "source_url": null, "captured_at": null, "author": null, "contributor": null},
    {"id": "server_compliance_types_ComplianceAuditLog", "label": "ComplianceAuditLog — immutable audit entry with SHA-256 hash chain (hash + previousHash)", "file_type": "code", "source_file": "server/compliance-types.ts", "source_location": "L160-L191", "source_url": null, "captured_at": null, "author": null, "contributor": null},
    {"id": "server_compliance_types_ConsentRecord", "label": "ConsentRecord — COPPA/FERPA/GDPR consent with grantedBy field for parental consent flow", "file_type": "code", "source_file": "server/compliance-types.ts", "source_location": "L195-L217", "source_url": null, "captured_at": null, "author": null, "contributor": null},
    {"id": "server_compliance_types_DataBreachIncident", "label": "DataBreachIncident — breach tracking with 72h GDPR notification status", "file_type": "code", "source_file": "server/compliance-types.ts", "source_location": "L221-L249", "source_url": null, "captured_at": null, "author": null, "contributor": null},
    {"id": "server_compliance_types_ComplianceViolation", "label": "ComplianceViolation — violation record with severity, status, and remediation plan", "file_type": "code", "source_file": "server/compliance-types.ts", "source_location": "L281-L292", "source_url": null, "captured_at": null, "author": null, "contributor": null},
    {"id": "server_compliance_types_DataDeletionRequest", "label": "DataDeletionRequest — framework-specific deletion with per-category retention periods", "file_type": "code", "source_file": "server/compliance-types.ts", "source_location": "L122-L157", "source_url": null, "captured_at": null, "author": null, "contributor": null},
    {"id": "server_core_server_coreServerEntrypoint", "label": "core-server.ts — lean production entrypoint: Node + Postgres only, port 4000", "file_type": "code", "source_file": "server/core-server.ts", "source_location": null, "source_url": null, "captured_at": null, "author": null, "contributor": null},
    {"id": "server_core_server_routeMounting", "label": "Route mounting order: payments, rankings, athletes, messages, training, users, programs, coaches, coach, auth, upload, admin, mainApi", "file_type": "code", "source_file": "server/core-server.ts", "source_location": "L40-L54", "source_url": null, "captured_at": null, "author": null, "contributor": null},
    {"id": "server_cosmos_api_CosmosAPIService", "label": "CosmosAPIService — enterprise API service: Cosmos + Redis cache + event publishing", "file_type": "code", "source_file": "server/cosmos-api.ts", "source_location": "L89-L545", "source_url": null, "captured_at": null, "author": null, "contributor": null},
    {"id": "server_cosmos_api_cacheMiddleware", "label": "cacheMiddleware — HTTP GET response caching via global cacheAside singleton", "file_type": "code", "source_file": "server/cosmos-api.ts", "source_location": "L60-L85", "source_url": null, "captured_at": null, "author": null, "contributor": null},
    {"id": "server_cosmos_api_responseTimeTracker", "label": "responseTimeTracker — logs requests >200ms and records http_request_duration histogram", "file_type": "code", "source_file": "server/cosmos-api.ts", "source_location": "L22-L55", "source_url": null, "captured_at": null, "author": null, "contributor": null},
    {"id": "server_cosmos_repositories_CosmosRepository", "label": "CosmosRepository<T> — base class with point-read (<50ms target) and optimistic create", "file_type": "code", "source_file": "server/cosmos-repositories.ts", "source_location": "L13-L80", "source_url": null, "captured_at": null, "author": null, "contributor": null},
    {"id": "server_cosmos_schema_OptimizedCosmosClient", "label": "OptimizedCosmosClient — Cosmos DB client with container registry and RU consumption tracking", "file_type": "code", "source_file": "server/cosmos-schema.ts", "source_location": null, "source_url": null, "captured_at": null, "author": null, "contributor": null},
    {"id": "server_cosmos_schema_COSMOS_SCHEMA", "label": "COSMOS_SCHEMA — container definitions: users(50K RU), posts(100K), messages(75K), audit-logs(15K)", "file_type": "code", "source_file": "server/cosmos-schema.ts", "source_location": "L50-L80", "source_url": null, "captured_at": null, "author": null, "contributor": null},
    {"id": "server_data_pipelines_DataExportPipeline", "label": "DataExportPipeline — collects user data from Cosmos, generates export files, uploads to Azure Blob", "file_type": "code", "source_file": "server/data-pipelines.ts", "source_location": "L23-L80", "source_url": null, "captured_at": null, "author": null, "contributor": null},
    {"id": "server_db_postgres_connectionPool", "label": "db.postgres.ts — pg Pool (max:100, min:10) + Drizzle ORM for PostgreSQL", "file_type": "code", "source_file": "server/db.postgres.ts", "source_location": null, "source_url": null, "captured_at": null, "author": null, "contributor": null},
    {"id": "server_db_dbConnection", "label": "db.ts — primary db export: pg Pool + Drizzle + schema (DATABASE_URL fallback to localhost:5432/hers365)", "file_type": "code", "source_file": "server/db.ts", "source_location": null, "source_url": null, "captured_at": null, "author": null, "contributor": null},
    {"id": "server_drizzle_config_drizzleConfig", "label": "drizzle.config.ts — schema=./schema.ts, dialect=postgresql, credentials from DATABASE_URL", "file_type": "code", "source_file": "server/drizzle.config.ts", "source_location": null, "source_url": null, "captured_at": null, "author": null, "contributor": null},
    {"id": "server_email_sendPasswordResetEmail", "label": "sendPasswordResetEmail — sends reset link via Resend (mocked if package missing)", "file_type": "code", "source_file": "server/email.ts", "source_location": "L39-L59", "source_url": null, "captured_at": null, "author": null, "contributor": null},
    {"id": "server_emailAuthRoutes_inMemoryResetTokens", "label": "In-memory reset token store (Map) with 1h TTL — not suitable for multi-instance production", "file_type": "code", "source_file": "server/emailAuthRoutes.ts", "source_location": "L117", "source_url": null, "captured_at": null, "author": null, "contributor": null},
    {"id": "server_emailAuthRoutes_emailAuthRouter", "label": "emailAuthRouter — /register, /login, /forgot-password, /reset-password for players only", "file_type": "code", "source_file": "server/emailAuthRoutes.ts", "source_location": null, "source_url": null, "captured_at": null, "author": null, "contributor": null},
    {"id": "server_emailAuthRoutes_emailEnumerationPrevention", "label": "forgot-password always returns 200 to prevent email enumeration", "file_type": "code", "source_file": "server/emailAuthRoutes.ts", "source_location": "L126-L127", "source_url": null, "captured_at": null, "author": null, "contributor": null}
  ],
  "edges": [
    {
      "source": "server_api_users_usersRouter",
      "target": "server_auth_jwtBearerMiddleware",
      "relation": "calls",
      "confidence": "EXTRACTED",
      "confidence_score": 1.0,
      "source_file": "server/api/users.ts",
      "source_location": "L8",
      "weight": 1.0
    },
    {
      "source": "server_api_users_usersRouter",
      "target": "server_db_dbConnection",
      "relation": "calls",
      "confidence": "EXTRACTED",
      "confidence_score": 1.0,
      "source_file": "server/api/users.ts",
      "source_location": "L33,L63,L77",
      "weight": 1.0
    },
    {
      "source": "server_api_users_roleBasedTableSelect",
      "target": "server_auth_UserRole",
      "relation": "references",
      "confidence": "EXTRACTED",
      "confidence_score": 1.0,
      "source_file": "server/api/users.ts",
      "source_location": "L16-L20",
      "weight": 0.9
    },
    {
      "source": "server_api_users_passwordHashStrip",
      "target": "server_api_users_usersRouter",
      "relation": "conceptually_related_to",
      "confidence": "EXTRACTED",
      "confidence_score": 1.0,
      "source_file": "server/api/users.ts",
      "source_location": "L35,L64",
      "weight": 0.8
    },
    {
      "source": "server_auth_requireAdmin",
      "target": "server_auth_jwtBearerMiddleware",
      "relation": "calls",
      "confidence": "EXTRACTED",
      "confidence_score": 1.0,
      "source_file": "server/auth.ts",
      "source_location": "L51",
      "weight": 1.0
    },
    {
      "source": "server_auth_requireCoach",
      "target": "server_auth_jwtBearerMiddleware",
      "relation": "calls",
      "confidence": "EXTRACTED",
      "confidence_score": 1.0,
      "source_file": "server/auth.ts",
      "source_location": "L66",
      "weight": 1.0
    },
    {
      "source": "server_auth_jwtBearerMiddleware",
      "target": "server_auth_signToken",
      "relation": "calls",
      "confidence": "EXTRACTED",
      "confidence_score": 1.0,
      "source_file": "server/auth.ts",
      "source_location": "L43",
      "weight": 1.0
    },
    {
      "source": "server_authRoutes_registerFlow",
      "target": "server_auth_bcryptHashCompare",
      "relation": "calls",
      "confidence": "EXTRACTED",
      "confidence_score": 1.0,
      "source_file": "server/authRoutes.ts",
      "source_location": "L67",
      "weight": 1.0
    },
    {
      "source": "server_authRoutes_registerFlow",
      "target": "server_auth_signToken",
      "relation": "calls",
      "confidence": "EXTRACTED",
      "confidence_score": 1.0,
      "source_file": "server/authRoutes.ts",
      "source_location": "L89",
      "weight": 1.0
    },
    {
      "source": "server_authRoutes_registerFlow",
      "target": "server_db_dbConnection",
      "relation": "calls",
      "confidence": "EXTRACTED",
      "confidence_score": 1.0,
      "source_file": "server/authRoutes.ts",
      "source_location": "L71,L78,L83",
      "weight": 1.0
    },
    {
      "source": "server_authRoutes_loginFlow",
      "target": "server_authRoutes_loginRateLimiter",
      "relation": "references",
      "confidence": "EXTRACTED",
      "confidence_score": 1.0,
      "source_file": "server/authRoutes.ts",
      "source_location": "L99",
      "weight": 1.0
    },
    {
      "source": "server_authRoutes_loginFlow",
      "target": "server_auth_bcryptHashCompare",
      "relation": "calls",
      "confidence": "EXTRACTED",
      "confidence_score": 1.0,
      "source_file": "server/authRoutes.ts",
      "source_location": "L111",
      "weight": 1.0
    },
    {
      "source": "server_authRoutes_loginFlow",
      "target": "server_auth_signToken",
      "relation": "calls",
      "confidence": "EXTRACTED",
      "confidence_score": 1.0,
      "source_file": "server/authRoutes.ts",
      "source_location": "L116",
      "weight": 1.0
    },
    {
      "source": "server_authRoutes_googleOAuthFlow",
      "target": "server_auth_verifyGoogleToken",
      "relation": "calls",
      "confidence": "EXTRACTED",
      "confidence_score": 1.0,
      "source_file": "server/authRoutes.ts",
      "source_location": "L133",
      "weight": 1.0
    },
    {
      "source": "server_authRoutes_googleOAuthFlow",
      "target": "server_auth_signToken",
      "relation": "calls",
      "confidence": "EXTRACTED",
      "confidence_score": 1.0,
      "source_file": "server/authRoutes.ts",
      "source_location": "L160",
      "weight": 1.0
    },
    {
      "source": "server_authRoutes_googleOAuthFlow",
      "target": "server_authRoutes_loginRateLimiter",
      "relation": "references",
      "confidence": "EXTRACTED",
      "confidence_score": 1.0,
      "source_file": "server/authRoutes.ts",
      "source_location": "L122",
      "weight": 1.0
    },
    {
      "source": "server_authRoutes_statelessLogout",
      "target": "server_auth_jwtBearerMiddleware",
      "relation": "conceptually_related_to",
      "confidence": "INFERRED",
      "confidence_score": 0.85,
      "source_file": "server/authRoutes.ts",
      "source_location": "L179-L182",
      "weight": 0.5
    },
    {
      "source": "server_cache_layer_HybridCacheManager",
      "target": "server_cache_layer_RedisCacheClient",
      "relation": "calls",
      "confidence": "EXTRACTED",
      "confidence_score": 1.0,
      "source_file": "server/cache-layer.ts",
      "source_location": "L221-L229",
      "weight": 1.0
    },
    {
      "source": "server_cache_layer_HybridCacheManager",
      "target": "server_cosmos_repositories_CosmosRepository",
      "relation": "calls",
      "confidence": "EXTRACTED",
      "confidence_score": 1.0,
      "source_file": "server/cache-layer.ts",
      "source_location": "L229",
      "weight": 1.0
    },
    {
      "source": "server_cache_layer_HybridCacheManager",
      "target": "server_cache_layer_invalidateUserRelatedCaches",
      "relation": "calls",
      "confidence": "EXTRACTED",
      "confidence_score": 1.0,
      "source_file": "server/cache-layer.ts",
      "source_location": "L283",
      "weight": 1.0
    },
    {
      "source": "server_cache_layer_cacheAside",
      "target": "server_cache_layer_HybridCacheManager",
      "relation": "calls",
      "confidence": "EXTRACTED",
      "confidence_score": 1.0,
      "source_file": "server/cache-layer.ts",
      "source_location": "L608",
      "weight": 1.0
    },
    {
      "source": "server_coachRoutes_requireCoachGate",
      "target": "server_auth_requireCoach",
      "relation": "calls",
      "confidence": "EXTRACTED",
      "confidence_score": 1.0,
      "source_file": "server/coachRoutes.ts",
      "source_location": "L16",
      "weight": 1.0
    },
    {
      "source": "server_coachRoutes_scoutingBoard",
      "target": "server_db_dbConnection",
      "relation": "calls",
      "confidence": "EXTRACTED",
      "confidence_score": 1.0,
      "source_file": "server/coachRoutes.ts",
      "source_location": "L199,L214,L240,L269,L290",
      "weight": 1.0
    },
    {
      "source": "server_coachRoutes_coachToAthleteMessage",
      "target": "server_db_dbConnection",
      "relation": "calls",
      "confidence": "EXTRACTED",
      "confidence_score": 1.0,
      "source_file": "server/coachRoutes.ts",
      "source_location": "L344",
      "weight": 1.0
    },
    {
      "source": "server_coachRoutes_coachToAthleteMessage",
      "target": "server_coachRoutes_requireCoachGate",
      "relation": "conceptually_related_to",
      "confidence": "INFERRED",
      "confidence_score": 0.95,
      "source_file": "server/coachRoutes.ts",
      "source_location": "L16,L338",
      "weight": 0.8
    },
    {
      "source": "server_compliance_monitoring_ComplianceMonitor",
      "target": "server_cosmos_schema_OptimizedCosmosClient",
      "relation": "calls",
      "confidence": "EXTRACTED",
      "confidence_score": 1.0,
      "source_file": "server/compliance-monitoring.ts",
      "source_location": "L29",
      "weight": 1.0
    },
    {
      "source": "server_compliance_monitoring_violationPublish",
      "target": "server_compliance_types_ComplianceViolation",
      "relation": "references",
      "confidence": "EXTRACTED",
      "confidence_score": 1.0,
      "source_file": "server/compliance-monitoring.ts",
      "source_location": "L460",
      "weight": 1.0
    },
    {
      "source": "server_compliance_monitoring_violationPublish",
      "target": "server_compliance_monitoring_ComplianceAlerting",
      "relation": "calls",
      "confidence": "INFERRED",
      "confidence_score": 0.85,
      "source_file": "server/compliance-monitoring.ts",
      "source_location": "L476",
      "weight": 0.9
    },
    {
      "source": "server_compliance_monitoring_ComplianceAlerting",
      "target": "server_compliance_monitoring_ComplianceMonitor",
      "relation": "references",
      "confidence": "EXTRACTED",
      "confidence_score": 1.0,
      "source_file": "server/compliance-monitoring.ts",
      "source_location": "L671",
      "weight": 1.0
    },
    {
      "source": "server_compliance_monitoring_COPPACheck",
      "target": "server_compliance_types_ComplianceViolation",
      "relation": "references",
      "confidence": "INFERRED",
      "confidence_score": 0.85,
      "source_file": "server/compliance-monitoring.ts",
      "source_location": "L140-L181",
      "weight": 0.8
    },
    {
      "source": "server_compliance_orchestrator_ComplianceOrchestrator",
      "target": "server_compliance_service_ComplianceService",
      "relation": "calls",
      "confidence": "EXTRACTED",
      "confidence_score": 1.0,
      "source_file": "server/compliance-orchestrator.ts",
      "source_location": "L67-L70",
      "weight": 1.0
    },
    {
      "source": "server_compliance_orchestrator_ComplianceOrchestrator",
      "target": "server_compliance_monitoring_ComplianceMonitor",
      "relation": "calls",
      "confidence": "EXTRACTED",
      "confidence_score": 1.0,
      "source_file": "server/compliance-orchestrator.ts",
      "source_location": "L83-L86",
      "weight": 1.0
    },
    {
      "source": "server_compliance_orchestrator_ComplianceOrchestrator",
      "target": "server_data_pipelines_DataExportPipeline",
      "relation": "calls",
      "confidence": "EXTRACTED",
      "confidence_score": 1.0,
      "source_file": "server/compliance-orchestrator.ts",
      "source_location": "L72-L76",
      "weight": 1.0
    },
    {
      "source": "server_compliance_orchestrator_serviceBusEventHandlers",
      "target": "server_data_pipelines_DataExportPipeline",
      "relation": "calls",
      "confidence": "EXTRACTED",
      "confidence_score": 1.0,
      "source_file": "server/compliance-orchestrator.ts",
      "source_location": "L141",
      "weight": 1.0
    },
    {
      "source": "server_compliance_orchestrator_serviceBusEventHandlers",
      "target": "server_compliance_monitoring_ComplianceAlerting",
      "relation": "calls",
      "confidence": "EXTRACTED",
      "confidence_score": 1.0,
      "source_file": "server/compliance-orchestrator.ts",
      "source_location": "L189",
      "weight": 1.0
    },
    {
      "source": "server_compliance_orchestrator_ComplianceDashboard",
      "target": "server_compliance_orchestrator_ComplianceOrchestrator",
      "relation": "calls",
      "confidence": "EXTRACTED",
      "confidence_score": 1.0,
      "source_file": "server/compliance-orchestrator.ts",
      "source_location": "L358",
      "weight": 1.0
    },
    {
      "source": "server_compliance_service_ComplianceService",
      "target": "server_compliance_service_rbacMiddleware",
      "relation": "calls",
      "confidence": "EXTRACTED",
      "confidence_score": 1.0,
      "source_file": "server/compliance-service.ts",
      "source_location": "L63",
      "weight": 1.0
    },
    {
      "source": "server_compliance_service_ComplianceService",
      "target": "server_compliance_service_AuditChain",
      "relation": "calls",
      "confidence": "EXTRACTED",
      "confidence_score": 1.0,
      "source_file": "server/compliance-service.ts",
      "source_location": "L42",
      "weight": 1.0
    },
    {
      "source": "server_compliance_service_dataExportRequest",
      "target": "server_compliance_types_DataDeletionRequest",
      "relation": "shares_data_with",
      "confidence": "INFERRED",
      "confidence_score": 0.75,
      "source_file": "server/compliance-service.ts",
      "source_location": "L274",
      "weight": 0.6
    },
    {
      "source": "server_compliance_service_dataDeletionRequest",
      "target": "server_compliance_types_DataDeletionRequest",
      "relation": "references",
      "confidence": "EXTRACTED",
      "confidence_score": 1.0,
      "source_file": "server/compliance-service.ts",
      "source_location": "L357",
      "weight": 1.0
    },
    {
      "source": "server_compliance_service_rbacMiddleware",
      "target": "server_compliance_service_correlationIdMiddleware",
      "relation": "references",
      "confidence": "EXTRACTED",
      "confidence_score": 1.0,
      "source_file": "server/compliance-service.ts",
      "source_location": "L131",
      "weight": 0.8
    },
    {
      "source": "server_compliance_service_AuditChain",
      "target": "server_compliance_types_ComplianceAuditLog",
      "relation": "implements",
      "confidence": "EXTRACTED",
      "confidence_score": 1.0,
      "source_file": "server/compliance-service.ts",
      "source_location": "L474-L510",
      "weight": 1.0
    },
    {
      "source": "server_cosmos_api_CosmosAPIService",
      "target": "server_cache_layer_HybridCacheManager",
      "relation": "calls",
      "confidence": "EXTRACTED",
      "confidence_score": 1.0,
      "source_file": "server/cosmos-api.ts",
      "source_location": "L164",
      "weight": 1.0
    },
    {
      "source": "server_cosmos_api_CosmosAPIService",
      "target": "server_cosmos_schema_OptimizedCosmosClient",
      "relation": "calls",
      "confidence": "EXTRACTED",
      "confidence_score": 1.0,
      "source_file": "server/cosmos-api.ts",
      "source_location": "L156",
      "weight": 1.0
    },
    {
      "source": "server_cosmos_api_CosmosAPIService",
      "target": "server_cosmos_repositories_CosmosRepository",
      "relation": "calls",
      "confidence": "EXTRACTED",
      "confidence_score": 1.0,
      "source_file": "server/cosmos-api.ts",
      "source_location": "L160",
      "weight": 1.0
    },
    {
      "source": "server_cosmos_api_cacheMiddleware",
      "target": "server_cache_layer_cacheAside",
      "relation": "calls",
      "confidence": "EXTRACTED",
      "confidence_score": 1.0,
      "source_file": "server/cosmos-api.ts",
      "source_location": "L65",
      "weight": 1.0
    },
    {
      "source": "server_cosmos_api_responseTimeTracker",
      "target": "server_cosmos_api_CosmosAPIService",
      "relation": "references",
      "confidence": "EXTRACTED",
      "confidence_score": 1.0,
      "source_file": "server/cosmos-api.ts",
      "source_location": "L106",
      "weight": 0.7
    },
    {
      "source": "server_cosmos_repositories_CosmosRepository",
      "target": "server_cosmos_schema_OptimizedCosmosClient",
      "relation": "calls",
      "confidence": "EXTRACTED",
      "confidence_score": 1.0,
      "source_file": "server/cosmos-repositories.ts",
      "source_location": "L18-L22",
      "weight": 1.0
    },
    {
      "source": "server_data_pipelines_DataExportPipeline",
      "target": "server_cosmos_schema_OptimizedCosmosClient",
      "relation": "calls",
      "confidence": "EXTRACTED",
      "confidence_score": 1.0,
      "source_file": "server/data-pipelines.ts",
      "source_location": "L30",
      "weight": 1.0
    },
    {
      "source": "server_data_pipelines_DataExportPipeline",
      "target": "server_compliance_types_DataDeletionRequest",
      "relation": "references",
      "confidence": "EXTRACTED",
      "confidence_score": 1.0,
      "source_file": "server/data-pipelines.ts",
      "source_location": "L19",
      "weight": 0.8
    },
    {
      "source": "server_core_server_coreServerEntrypoint",
      "target": "server_authRoutes_registerFlow",
      "relation": "calls",
      "confidence": "EXTRACTED",
      "confidence_score": 1.0,
      "source_file": "server/core-server.ts",
      "source_location": "L49",
      "weight": 1.0
    },
    {
      "source": "server_core_server_coreServerEntrypoint",
      "target": "server_coachRoutes_requireCoachGate",
      "relation": "calls",
      "confidence": "EXTRACTED",
      "confidence_score": 1.0,
      "source_file": "server/core-server.ts",
      "source_location": "L48",
      "weight": 1.0
    },
    {
      "source": "server_core_server_coreServerEntrypoint",
      "target": "server_emailAuthRoutes_emailAuthRouter",
      "relation": "calls",
      "confidence": "EXTRACTED",
      "confidence_score": 1.0,
      "source_file": "server/core-server.ts",
      "source_location": "L50",
      "weight": 1.0
    },
    {
      "source": "server_core_server_coreServerEntrypoint",
      "target": "server_api_users_usersRouter",
      "relation": "calls",
      "confidence": "EXTRACTED",
      "confidence_score": 1.0,
      "source_file": "server/core-server.ts",
      "source_location": "L45",
      "weight": 1.0
    },
    {
      "source": "server_core_server_coreServerEntrypoint",
      "target": "server_db_dbConnection",
      "relation": "shares_data_with",
      "confidence": "INFERRED",
      "confidence_score": 0.95,
      "source_file": "server/core-server.ts",
      "source_location": null,
      "weight": 0.9
    },
    {
      "source": "server_emailAuthRoutes_emailAuthRouter",
      "target": "server_db_dbConnection",
      "relation": "calls",
      "confidence": "EXTRACTED",
      "confidence_score": 1.0,
      "source_file": "server/emailAuthRoutes.ts",
      "source_location": "L43,L85,L124",
      "weight": 1.0
    },
    {
      "source": "server_emailAuthRoutes_emailAuthRouter",
      "target": "server_email_sendPasswordResetEmail",
      "relation": "calls",
      "confidence": "EXTRACTED",
      "confidence_score": 1.0,
      "source_file": "server/emailAuthRoutes.ts",
      "source_location": "L130",
      "weight": 1.0
    },
    {
      "source": "server_emailAuthRoutes_inMemoryResetTokens",
      "target": "server_emailAuthRoutes_emailAuthRouter",
      "relation": "conceptually_related_to",
      "confidence": "EXTRACTED",
      "confidence_score": 1.0,
      "source_file": "server/emailAuthRoutes.ts",
      "source_location": "L117",
      "weight": 0.7
    },
    {
      "source": "server_emailAuthRoutes_emailEnumerationPrevention",
      "target": "server_emailAuthRoutes_emailAuthRouter",
      "relation": "conceptually_related_to",
      "confidence": "EXTRACTED",
      "confidence_score": 1.0,
      "source_file": "server/emailAuthRoutes.ts",
      "source_location": "L126-L127",
      "weight": 0.7
    },
    {
      "source": "server_db_dbConnection",
      "target": "server_drizzle_config_drizzleConfig",
      "relation": "references",
      "confidence": "INFERRED",
      "confidence_score": 0.85,
      "source_file": "server/db.ts",
      "source_location": null,
      "weight": 0.7
    },
    {
      "source": "server_db_postgres_connectionPool",
      "target": "server_db_dbConnection",
      "relation": "semantically_similar_to",
      "confidence": "INFERRED",
      "confidence_score": 0.75,
      "source_file": "server/db.postgres.ts",
      "source_location": null,
      "weight": 0.5
    },
    {
      "source": "server_compliance_orchestrator_ComplianceOrchestrator",
      "target": "server_compliance_orchestrator_compliancePort4001",
      "relation": "references",
      "confidence": "EXTRACTED",
      "confidence_score": 1.0,
      "source_file": "server/compliance-orchestrator.ts",
      "source_location": "L219",
      "weight": 0.9
    },
    {
      "source": "server_core_server_coreServerEntrypoint",
      "target": "server_compliance_orchestrator_compliancePort4001",
      "relation": "conceptually_related_to",
      "confidence": "INFERRED",
      "confidence_score": 0.85,
      "source_file": "server/core-server.ts",
      "source_location": null,
      "weight": 0.6
    },
    {
      "source": "server_coachRoutes_coachToAthleteMessage",
      "target": "server_compliance_monitoring_FERPACheck",
      "relation": "conceptually_related_to",
      "confidence": "INFERRED",
      "confidence_score": 0.75,
      "source_file": "server/coachRoutes.ts",
      "source_location": "L338-L358",
      "weight": 0.7
    },
    {
      "source": "server_compliance_types_ConsentRecord",
      "target": "server_compliance_monitoring_COPPACheck",
      "relation": "shares_data_with",
      "confidence": "INFERRED",
      "confidence_score": 0.85,
      "source_file": "server/compliance-types.ts",
      "source_location": null,
      "weight": 0.8
    },
    {
      "source": "server_compliance_types_DataBreachIncident",
      "target": "server_compliance_monitoring_GDPRCheck",
      "relation": "shares_data_with",
      "confidence": "INFERRED",
      "confidence_score": 0.85,
      "source_file": "server/compliance-types.ts",
      "source_location": null,
      "weight": 0.8
    },
    {
      "source": "server_cloud_storage_uploadVideo",
      "target": "server_cloud_config_cloudConfig",
      "relation": "references",
      "confidence": "INFERRED",
      "confidence_score": 0.75,
      "source_file": "server/cloud-storage.ts",
      "source_location": "L7-L13",
      "weight": 0.6
    },
    {
      "source": "server_cosmos_api_CosmosAPIService",
      "target": "server_compliance_service_ComplianceService",
      "relation": "conceptually_related_to",
      "confidence": "INFERRED",
      "confidence_score": 0.65,
      "source_file": "server/cosmos-api.ts",
      "source_location": "L148",
      "weight": 0.5
    }
  ],
  "hyperedges": [],
  "input_tokens": 0,
  "output_tokens": 0
}
